MANIFEST.in
README.md
requirements.txt
setup.py
AnalysisDataLink.egg-info/PKG-INFO
AnalysisDataLink.egg-info/SOURCES.txt
AnalysisDataLink.egg-info/dependency_links.txt
AnalysisDataLink.egg-info/requires.txt
AnalysisDataLink.egg-info/top_level.txt
analysisdatalink/__init__.py
analysisdatalink/datalink.py
analysisdatalink/datalink_base.py
analysisdatalink/datalink_ext.py
analysisdatalink/version_map.py
test/test_synapses.py