Metadata-Version: 2.1
Name: AnalysisDataLink
Version: 0.4.0
Summary: Tools to query data from the dynamic annotation framework
Home-page: https://github.com/seung-lab/AnalysisDataLink
Author: Forrest Collman, Sven Dorkenwald, Casey Schneider-Mizell
Author-email: caseysm@gmail.com
License: UNKNOWN
Platform: UNKNOWN
